mte/__init__.py
mte/client.py
mte/db.py
mte/districtcode.txt
mte/exeptions.py
mte/logger.py
mte/logger_config.py
mte/orm.py
mte/timehandler.py
mte/util.py
mte_orm-1.1.dist-info/METADATA
mte_orm-1.1.dist-info/RECORD
mte_orm-1.1.dist-info/WHEEL
mte_orm-1.1.dist-info/top_level.txt
