Metadata-Version: 2.1
Name: mte-orm
Version: 1.1
Summary: This is a api test module
Home-page: https://gitlab.rongxiaolu.com/Thomas/mte
Author: li
Author-email: run_ice_l@qq.com
License: GPLv3
Keywords: redis subscripe
Platform: UNKNOWN
Requires-Dist: nose
Requires-Dist: requests
Requires-Dist: sqlalchemy
Requires-Dist: requests-ntlm
